maskify/__init__.py
maskify/masker.py
maskify/masker_helper.py
tests/__init__.py
tests/test_masker.py
maskify_py-0.1.2.dist-info/LICENSE
maskify_py-0.1.2.dist-info/METADATA
maskify_py-0.1.2.dist-info/WHEEL
maskify_py-0.1.2.dist-info/entry_points.txt
maskify_py-0.1.2.dist-info/top_level.txt
maskify_py-0.1.2.dist-info/RECORD
