Metadata-Version: 2.1
Name: maskify-py
Version: 0.1.2
Summary: Maskify is a lightweight, flexible library for Python, inspired by the Maskify.Core library for .NET. It helps developers securely mask sensitive data, such as Brazilian documents (CPF, CNPJ), emails, credit cards, and phone numbers. This library provides built-in masking for common data types, along with customizable masking options to ensure compliance with data protection regulations.
Home-page: https://github.com/ninjapythonbrasil/maskify-py
Author: Raphael Augusto Ferroni Cardoso
Author-email: rferronicardoso@gmail.com
Classifier: Programming Language :: Python :: 3
Classifier: License :: OSI Approved :: MIT License
Classifier: Operating System :: OS Independent
Requires-Python: >=3.6
License-File: LICENSE
Requires-Dist: requests
Requires-Dist: numpy
Provides-Extra: dev
Requires-Dist: pytest; extra == "dev"
Requires-Dist: black; extra == "dev"
